LICENSE.txt
MANIFEST.in
README.txt
build_distribution.bat
get_requirements.bat
pavement.py
paver-minilib.zip
setup.py
docs/Makefile
docs/conf.py
docs/ec_intro.rst
docs/examples.rst
docs/index.rst
docs/make.bat
docs/moonshot.jpg
docs/moonshot.py
docs/polyarea.py
docs/rastrigin.py
docs/reference.rst
docs/swarm_intro.rst
docs/tutorial.rst
ecspy/__init__.py
ecspy/analysis.py
ecspy/archivers.py
ecspy/benchmarks.py
ecspy/ec.py
ecspy/emo.py
ecspy/evaluators.py
ecspy/migrators.py
ecspy/observers.py
ecspy/replacers.py
ecspy/selectors.py
ecspy/swarm.py
ecspy/terminators.py
ecspy/topologies.py
ecspy.egg-info/PKG-INFO
ecspy.egg-info/SOURCES.txt
ecspy.egg-info/dependency_links.txt
ecspy.egg-info/top_level.txt
ecspy/contrib/__init__.py
ecspy/contrib/approximate.py
ecspy/contrib/cgp.py
ecspy/contrib/micro.py
ecspy/contrib/utils.py
ecspy/contrib/smcgp/encoding.py
ecspy/contrib/smcgp/modification_functions.py
ecspy/contrib/smcgp/phenotype.py
ecspy/variators/__init__.py
ecspy/variators/crossovers.py
ecspy/variators/mutators.py
ecspy/variators/variators.py
examples/__init__.py
examples/cgp_example.py
examples/constraint_example.py
examples/custom_ec_example.py
examples/dea_example.py
examples/eda_example.py
examples/es_example.py
examples/ga_example.py
examples/infinite_monkey_theorem.py
examples/niche_example.py
examples/nsga_example.py
examples/paes_example.py
examples/pso_example.py
examples/sa_example.py
examples/smcgp_parity_example.py
tests/__init__.py
tests/example_tests.py
tests/operator_tests.py
tests/smcgp_test.py