Metadata-Version: 1.0
Name: ecspy
Version: 1.1
Summary: A framework for creating evolutionary computations in Python.
Home-page: http://ecspy.googlecode.com
Author: Aaron Garrett
Author-email: aaron.lee.garrett@gmail.com
License: GPLv3+
Download-URL: http://ecspy.googlecode.com/files/ecspy-1.1.zip
Keywords: python,optimization,evolutionary,computation,genetic algorithm,particle swarm,estimation of distribution,differential evolution,nsga,paes
Platform: Any
Classifier: Development Status :: 5 - Production/Stable
Classifier: Environment :: Console
Classifier: Intended Audience :: Developers
Classifier: Intended Audience :: Science/Research
Classifier: License :: OSI Approved :: GNU General Public License (GPL)
Classifier: Operating System :: OS Independent
Classifier: Programming Language :: Python :: 2
Classifier: Topic :: Scientific/Engineering :: Artificial Intelligence
